astx/__init__.py
astx/base.py
astx/blocks.py
astx/callables.py
astx/classes.py
astx/comprehensions.py
astx/context_manager.py
astx/data.py
astx/exceptions.py
astx/flows.py
astx/literals/__init__.py
astx/literals/base.py
astx/literals/boolean.py
astx/literals/collections.py
astx/literals/numeric.py
astx/literals/string.py
astx/literals/temporal.py
astx/mixes.py
astx/modifiers.py
astx/operators.py
astx/packages.py
astx/py.typed
astx/subscript.py
astx/symbol_table.py
astx/tools/__init__.py
astx/tools/typing.py
astx/types/__init__.py
astx/types/base.py
astx/types/boolean.py
astx/types/casting.py
astx/types/collections.py
astx/types/numeric.py
astx/types/operators.py
astx/types/string.py
astx/types/temporal.py
astx/types/ttypes.py
astx/viz.py
astx-0.23.1.dist-info/METADATA
astx-0.23.1.dist-info/WHEEL
astx-0.23.1.dist-info/RECORD
